LICENSE
MANIFEST.in
README.rst
setup.cfg
setup.py
dendrogram_ts/__init__.py
dendrogram_ts/dendrogram_ts.py
dendrogram_ts.egg-info/PKG-INFO
dendrogram_ts.egg-info/SOURCES.txt
dendrogram_ts.egg-info/dependency_links.txt
dendrogram_ts.egg-info/requires.txt
dendrogram_ts.egg-info/top_level.txt