Metadata-Version: 2.1
Name: dendrogram-ts
Version: 0.1.1
Summary: Plotting time-series graphs in scipy's dendrogram
Home-page: https://github.com/mapattacker/dendrogram-ts
Author: Jake Teo
Author-email: mapattacker@gmail.com
License: MIT
Download-URL: https://github.com/mapattacker/dendrogram-ts/archive/refs/tags/v0.1.1.tar.gz
Keywords: dendrogram,agglomerative clustering,timeseries
Platform: UNKNOWN
Classifier: Development Status :: 4 - Beta
Classifier: Intended Audience :: Developers
Classifier: Topic :: Software Development :: Build Tools
Classifier: License :: OSI Approved :: MIT License
Classifier: Programming Language :: Python :: 3.6
Classifier: Programming Language :: Python :: 3.7
Classifier: Programming Language :: Python :: 3.8
